Lab3/Lab3Code/alu.v
/***************************************************
Student Name:
Student ID:
***************************************************/
`timescale 1ns/1ps

module alu(
	input                   rst_n,         // negative reset            (input)
	input	signed    [32-1:0]	src1,          // 32 bits source 1          (input)
	input	signed     [32-1:0]	src2,          // 32 bits source 2          (input)
	input 	     [ 4-1:0] 	ALU_control,   // 4 bits ALU control input  (input)
	output reg   [32-1:0]	result,        // 32 bits result            (output)
	output reg              zero,          // 1 bit when the output is 0, zero must be set (output)
	output reg              cout,          // 1 bit carry out           (output)
	output reg              overflow       // 1 bit overflow            (output)
	);

/* Write your code HERE */
always @(negedge rst_n) begin
	if(~rst_n)begin
		result<=0;
		zero<=0;
		cout<=0;
		overflow<=0;

	end
end

always @(*)begin
	case(ALU_control)
			4'b0010:begin	//add
				{cout,result}={1'b0,src1}+{1'b0,src2};
			end
			4'b0110:begin	//sub
				{cout,result}={1'b0,src1}+{1'b0,~src2}+1;
			end
			4'b0000:begin	//and
				result=src1&src2;
			end
			4'b0001:begin	//or
				result=src1|src2;
			end
			4'b0011:begin	//xor
				result=src1^src2;
			end
			4'b0111:begin	//slt
				result=src1<src2;
				end
			4'b1000:begin	//sll
				result=src1<<src2;
			end
			4'b1001:begin	//sra
				result=src1>>>src2;
			end
			default: ;
	endcase

end

always @(*) begin
	if(ALU_control==4'b0010)begin
		//add
		if(src1[31]==0 && src2[31]==0 && result[31]==1)
			overflow=1;
		else if(src1[31]==1 && src2[31]==1 && result[31]==0)
			overflow=1;
		
		else
			overflow=0;
	end
	else if(ALU_control==4'b0110)begin
		//sub
		if(src1[31]==0 && src2[31]==1 && result[31]==1)
			overflow=1;
		else if(src1[31]==1 && src2[31]==0 && result[31]==0)
			overflow=1;
		else
			overflow=0;
	end
	else begin
		overflow=0;
		cout=0;
	end
	zero<=~(|result);
end



endmodule

Lab3/Lab3Code/ALU_Ctrl.v
/***************************************************
Student Name: 
Student ID: 
***************************************************/

`timescale 1ns/1ps

module ALU_Ctrl(
	input	[4-1:0]	instr,
	input	[2-1:0]	ALUOp,
	output	reg [4-1:0] ALU_Ctrl_o
	);
	
/* Write your code HERE */
always @(*)begin
	if(ALUOp[1])begin	//R-type:1X
		case(instr)
			4'b0000:begin	//add
				ALU_Ctrl_o=4'b0010;
			end
			4'b1000:begin	//sub
				ALU_Ctrl_o=4'b0110;
			end
			4'b0111:begin	//and
				ALU_Ctrl_o=4'b0000;
			end
			4'b0110:begin	//or
				ALU_Ctrl_o=4'b0001;
			end
			4'b0100:begin	//xor
				ALU_Ctrl_o=4'b0011;
			end
			4'b0010:begin	//slt
				ALU_Ctrl_o=4'b0111;
			end
			4'b0001:begin	//sll
				ALU_Ctrl_o=4'b1000;
			end
			4'b1101:begin	//sra
				ALU_Ctrl_o=4'b1001;
			end


	endcase
	end
end



endmodule

Lab3/Lab3Code/Adder.v
/***************************************************
Student Name: 
Student ID: 
***************************************************/

`timescale 1ns/1ps

module Adder(
    input  [32-1:0] src1_i,
	input  [32-1:0] src2_i,
	output [32-1:0] sum_o
	);
    
/* Write your code HERE */

assign sum_o= src1_i + src2_i;


endmodule

Lab3/Lab3Code/Decoder.v
/***************************************************
Student Name: 
Student ID: 
***************************************************/

`timescale 1ns/1ps

module Decoder(
	input [32-1:0] 	instr_i,
	output wire			ALUSrc,
	output wire			RegWrite,
	output wire			Branch,
	output wire [2-1:0]	ALUOp
	);
	
//Internal Signals
wire	[7-1:0]		opcode;
wire 	[3-1:0]		funct3;
wire	[4-1:0]		func_field;
wire	[9-1:0]		Ctrl_o;

assign opcode=instr_i[6:0];
assign func_field={instr_i[30],instr_i[14:12]};

reg tp_alusrc;
reg tp_reg;
reg tp_brn;
reg [1:0]tp_op;

always @(*) begin	
	case(opcode)
		7'b0110011:begin
		tp_alusrc=0;
		tp_reg=1;
		tp_brn=0;
		tp_op=2'b1x;

		end

	endcase
end

assign ALUSrc=tp_alusrc;
assign RegWrite=tp_reg;
assign Branch=tp_brn;
assign ALUOp[0]=tp_op[0];
assign ALUOp[1]=tp_op[1];




endmodule

Lab3/Lab3test/Reg_File.v
/***************************************************
Student Name: 
Student ID: 
***************************************************/

`timescale 1ns/1ps

module Reg_File(
    input           	 clk_i,
	input           	 rst_i,
    input  		[5-1:0]  RSaddr_i,
    input  		[5-1:0]  RTaddr_i,
    input  		[5-1:0]  RDaddr_i,
    input  		[32-1:0] RDdata_i,
    input           	 RegWrite_i,
    output wire [32-1:0] RSdata_o,
    output wire [32-1:0] RTdata_o
    );
          
reg signed [32-1:0] Reg_File [0:32-1];     

assign RSdata_o = Reg_File[RSaddr_i] ;
assign RTdata_o = Reg_File[RTaddr_i] ;   

always @(posedge clk_i) begin
    if(~rst_i) begin
	    Reg_File[0]  <= 0; Reg_File[1]  <= 1; Reg_File[2]  <= 2; Reg_File[3]  <= 0;
	    Reg_File[4]  <= 0; Reg_File[5]  <= 0; Reg_File[6]  <= 0; Reg_File[7]  <= 0;
        Reg_File[8]  <= 0; Reg_File[9]  <= 0; Reg_File[10] <= 0; Reg_File[11] <= 0;
	    Reg_File[12] <= 0; Reg_File[13] <= 0; Reg_File[14] <= 0; Reg_File[15] <= 0;
        Reg_File[16] <= 0; Reg_File[17] <= 0; Reg_File[18] <= 0; Reg_File[19] <= 0;      
        Reg_File[20] <= 0; Reg_File[21] <= 0; Reg_File[22] <= 0; Reg_File[23] <= 0;
        Reg_File[24] <= 0; Reg_File[25] <= 0; Reg_File[26] <= 0; Reg_File[27] <= 0;
        Reg_File[28] <= 0; Reg_File[29] <= 0; Reg_File[30] <= 0; Reg_File[31] <= 0;
	end
    else begin
        if(RegWrite_i) 
            Reg_File[RDaddr_i] <= RDdata_i;	
		else 
		    Reg_File[RDaddr_i] <= Reg_File[RDaddr_i];
	end
end

endmodule

Lab3/Lab3Code/Instr_Memory.v
/***************************************************
Student Name: 
Student ID: 
***************************************************/

`timescale 1ns/1ps

module Instr_Memory(
    input 	    [32-1:0] 	 addr_i,
	output wire [32-1:0] 	 instr_o
);

integer          i;
reg		[32-1:0] instruction_file	[0:31];

initial begin
    for ( i=0; i<32; i=i+1 )
	    instruction_file[i] = 32'b0;
    $readmemb("CO_test_data10.txt", instruction_file); 
end

assign	instr_o = instruction_file[addr_i/4];

endmodule

Lab4/ProgramCounter.v
/***************************************************
Student Name:許舒茵
Student ID: 0816080
***************************************************/

   `timescale 1ns/1ps

   module ProgramCounter(
       input               clk_i,
       input               rst_i,
       input      [32-1:0] pc_i,
       output reg [32-1:0] pc_o
   );

   always @(posedge clk_i) begin
       if(~rst_i)
           pc_o <= 0;
       else
           pc_o <= pc_i;
   end

   endmodule

Lab3/Lab3Code/Simple_Single_CPU.v
/***************************************************
Student Name: 
Student ID: 
***************************************************/

`timescale 1ns/1ps
module Simple_Single_CPU(
	input clk_i,
	input rst_i
	);

//Internal Signles
wire [31:0] pc_i;
wire [31:0] pc_o;
wire [31:0] instr;
wire [31:0] ALUresult;
wire RegWrite;
wire [31:0] RSdata_o;
wire [31:0] RTdata_o;
wire ALUSrc;
wire [1:0] ALUOp;
wire [3:0]ALU_control;
wire zero,cout,overflow;
wire [31:0]imm_4 = 4;
		
ProgramCounter PC(
        .clk_i(clk_i),      
	    .rst_i (rst_i),     
	    .pc_i(pc_i) ,   
	    .pc_o(pc_o) 
	    );

Instr_Memory IM(
        .addr_i(pc_o),  
	    .instr_o(instr)    
	    );
		
Reg_File RF(
        .clk_i(clk_i),      
	    .rst_i(rst_i) ,     
        .RSaddr_i(instr[19:15]) ,  
        .RTaddr_i(instr[24:20]) ,  
        .RDaddr_i(instr[11:7]) ,  
        .RDdata_i(ALUresult)  , 
        .RegWrite_i (RegWrite),
        .RSdata_o(RSdata_o) ,  
        .RTdata_o(RTdata_o)   
        );
		
Decoder Decoder(
	.instr_i(instr),
	.ALUSrc(ALUSrc),
	.RegWrite(RegWrite),
	.Branch(Branch),
	.ALUOp(ALUOp)
	    );	

Adder PC_plus_4_Adder(
	.src1_i(pc_o),
	.src2_i(imm_4),
	.sum_o(pc_i)
	    );
		
	
			
ALU_Ctrl ALU_Ctrl(
	.instr({instr[30],instr[14:12]}),
	.ALUOp(ALUOp),
	.ALU_Ctrl_o(ALU_control)
		);
		
alu alu(
	.rst_n(rst_i), 
	.src1(RSdata_o),
	.src2(RTdata_o),
	.ALU_control(ALU_control),
	.result(ALUresult),
	.zero(zero), 
	.cout(cout),
	.overflow(overflow)    
		);
	
		
endmodule

Lab3/Lab3test/testbench.v
/***************************************************
Student Name: 
Student ID: 
***************************************************/

`timescale 1ns/1ps
`define CYCLE_TIME 10			
`define END_COUNT 100

module testbench;

reg         clk;
reg         rst_n;
integer     count;
integer     fp_w;

Simple_Single_CPU cpu(
        .clk_i(clk),
		.rst_i(rst_n)
		);

always #(`CYCLE_TIME/2) clk = ~clk;	

initial begin
	$dumpfile("lab3.vcd");
    $dumpvars(0, testbench);
end
	
initial  begin
    fp_w = $fopen("CO_Result.txt");
	clk = 0;
    rst_n = 0;
	count = 0;
    #(`CYCLE_TIME)      rst_n = 1;
    #(`CYCLE_TIME*`END_COUNT)	$fclose(fp_w); $finish;
end

always@(posedge clk) begin
    count = count + 1;
	if( count == `END_COUNT ) begin 
    $fdisplay(fp_w, "r0 = %3d, r1 = %3d, r2 = %3d, r3 = %3d, \nr4 = %3d, r5 = %3d, r6 = %3d, r7 = %3d, \nr8 = %3d, r9 = %3d, r10 = %2d, r11 = %2d",
	          cpu.RF.Reg_File[0], cpu.RF.Reg_File[1], cpu.RF.Reg_File[2], cpu.RF.Reg_File[3], cpu.RF.Reg_File[4], 
			  cpu.RF.Reg_File[5], cpu.RF.Reg_File[6], cpu.RF.Reg_File[7], cpu.RF.Reg_File[8], cpu.RF.Reg_File[9], 
			  cpu.RF.Reg_File[10],cpu.RF.Reg_File[11]
			  );
	$display("r0 = %3d, r1 = %3d, r2 = %3d, r3 = %3d, \nr4 = %3d, r5 = %3d, r6 = %3d, r7 = %3d, \nr8 = %3d, r9 = %3d, r10 = %2d, r11 = %2d",
	          cpu.RF.Reg_File[0], cpu.RF.Reg_File[1], cpu.RF.Reg_File[2], cpu.RF.Reg_File[3], cpu.RF.Reg_File[4], 
			  cpu.RF.Reg_File[5], cpu.RF.Reg_File[6], cpu.RF.Reg_File[7], cpu.RF.Reg_File[8], cpu.RF.Reg_File[9], 
			  cpu.RF.Reg_File[10],cpu.RF.Reg_File[11]
			  );
	end
end
  
endmodule

Lab3/Lab3Code/lab3.vcd
$date
	Fri Apr 23 20:51:14 2021
$end
$version
	Icarus Verilog
$end
$timescale
	1ps
$end
$scope module testbench $end
$var reg 1 ! clk $end
$var reg 1 " rst_n $end
$var integer 32 # count [31:0] $end
$var integer 32 $ fp_w [31:0] $end
$scope module cpu $end
$var wire 1 ! clk_i $end
$var wire 32 % imm_4 [31:0] $end
$var wire 1 " rst_i $end
$var wire 1 & zero $end
$var wire 32 ' pc_o [31:0] $end
$var wire 32 ( pc_i [31:0] $end
$var wire 1 ) overflow $end
$var wire 32 * instr [31:0] $end
$var wire 1 + cout $end
$var wire 1 , RegWrite $end
$var wire 32 - RTdata_o [31:0] $end
$var wire 32 . RSdata_o [31:0] $end
$var wire 1 / Branch $end
$var wire 32 0 ALUresult [31:0] $end
$var wire 4 1 ALU_control [3:0] $end
$var wire 1 2 ALUSrc $end
$var wire 2 3 ALUOp [1:0] $end
$scope module ALU_Ctrl $end
$var wire 4 4 instr [3:0] $end
$var wire 2 5 ALUOp [1:0] $end
$var reg 4 6 ALU_Ctrl_o [3:0] $end
$upscope $end
$scope module Decoder $end
$var wire 1 2 ALUSrc $end
$var wire 1 / Branch $end
$var wire 1 , RegWrite $end
$var wire 7 7 opcode [6:0] $end
$var wire 32 8 instr_i [31:0] $end
$var wire 4 9 func_field [3:0] $end
$var wire 2 : ALUOp [1:0] $end
$var reg 1 ; tp_alusrc $end
$var reg 1 < tp_brn $end
$var reg 2 = tp_op [1:0] $end
$var reg 1 > tp_reg $end
$upscope $end
$scope module IM $end
$var wire 32 ? instr_o [31:0] $end
$var wire 32 @ addr_i [31:0] $end
$var integer 32 A i [31:0] $end
$upscope $end
$scope module PC $end
$var wire 1 ! clk_i $end
$var wire 1 " rst_i $end
$var wire 32 B pc_i [31:0] $end
$var reg 32 C pc_o [31:0] $end
$upscope $end
$scope module PC_plus_4_Adder $end
$var wire 32 D src1_i [31:0] $end
$var wire 32 E src2_i [31:0] $end
$var wire 32 F sum_o [31:0] $end
$upscope $end
$scope module RF $end
$var wire 5 G RDaddr_i [4:0] $end
$var wire 5 H RSaddr_i [4:0] $end
$var wire 32 I RSdata_o [31:0] $end
$var wire 5 J RTaddr_i [4:0] $end
$var wire 32 K RTdata_o [31:0] $end
$var wire 1 , RegWrite_i $end
$var wire 1 ! clk_i $end
$var wire 1 " rst_i $end
$var wire 32 L RDdata_i [31:0] $end
$upscope $end
$scope module alu $end
$var wire 4 M ALU_control [3:0] $end
$var wire 1 " rst_n $end
$var wire 32 N src1 [31:0] $end
$var wire 32 O src2 [31:0] $end
$var reg 1 + cout $end
$var reg 1 ) overflow $end
$var reg 32 P result [31:0] $end
$var reg 1 & zero $end
$upscope $end
$upscope $end
$upscope $end
$enddefinitions $end
#0
$dumpvars
b0 P
bx O
bx N
bx M
b0 L
bx K
bx J
bx I
bx H
bx G
bx F
b100 E
bx D
bx C
bx B
b100000 A
bx @
bx ?
x>
bx =
x<
x;
bx :
bx 9
bx 8
bx 7
bx 6
bx 5
bx 4
bx 3
x2
bx 1
b0 0
x/
bx .
bx -
x,
0+
bx *
0)
bx (
bx '
1&
b100 %
b10 $
b0 #
0"
0!
$end
#5000
0&
b100 0
b100 L
b100 P
b1000 1
b1000 6
b1000 M
b1x 3
b1x 5
b1x :
b1x =
0/
0<
1,
1>
02
0;
b1 9
b110011 7
b1 4
b11 G
b10 -
b10 K
b10 O
b10 J
b1 .
b1 I
b1 N
b1 H
b100 (
b100 B
b100 F
b1000001001000110110011 *
b1000001001000110110011 8
b1000001001000110110011 ?
b0 '
b0 @
b0 C
b0 D
b1 #
1!
#10000
0!
1"
#15000
b1001 1
b1001 6
b1001 M
b10 0
b10 L
b10 P
b1101 9
b1101 4
b100 G
b1 -
b1 K
b1 O
b1 J
b100 .
b100 I
b100 N
b11 H
b1000 (
b1000 B
b1000 F
b1000000000100011101001000110011 *
b1000000000100011101001000110011 8
b1000000000100011101001000110011 ?
b100 '
b100 @
b100 C
b100 D
b10 #
1!
#20000
0!
#25000
1&
b10 1
b10 6
b10 M
b0 0
b0 L
b0 P
b0 9
b0 7
b0 4
b0 G
b0 -
b0 K
b0 O
b0 J
b0 .
b0 I
b0 N
b0 H
b1100 (
b1100 B
b1100 F
b0 *
b0 8
b0 ?
b1000 '
b1000 @
b1000 C
b1000 D
b11 #
1!
#30000
0!
#35000
b10000 (
b10000 B
b10000 F
b1100 '
b1100 @
b1100 C
b1100 D
b100 #
1!
#40000
0!
#45000
b10100 (
b10100 B
b10100 F
b10000 '
b10000 @
b10000 C
b10000 D
b101 #
1!
#50000
0!
#55000
b11000 (
b11000 B
b11000 F
b10100 '
b10100 @
b10100 C
b10100 D
b110 #
1!
#60000
0!
#65000
b11100 (
b11100 B
b11100 F
b11000 '
b11000 @
b11000 C
b11000 D
b111 #
1!
#70000
0!
#75000
b100000 (
b100000 B
b100000 F
b11100 '
b11100 @
b11100 C
b11100 D
b1000 #
1!
#80000
0!
#85000
b100100 (
b100100 B
b100100 F
b100000 '
b100000 @
b100000 C
b100000 D
b1001 #
1!
#90000
0!
#95000
b101000 (
b101000 B
b101000 F
b100100 '
b100100 @
b100100 C
b100100 D
b1010 #
1!
#100000
0!
#105000
b101100 (
b101100 B
b101100 F
b101000 '
b101000 @
b101000 C
b101000 D
b1011 #
1!
#110000
0!
#115000
b110000 (
b110000 B
b110000 F
b101100 '
b101100 @
b101100 C
b101100 D
b1100 #
1!
#120000
0!
#125000
b110100 (
b110100 B
b110100 F
b110000 '
b110000 @
b110000 C
b110000 D
b1101 #
1!
#130000
0!
#135000
b111000 (
b111000 B
b111000 F
b110100 '
b110100 @
b110100 C
b110100 D
b1110 #
1!
#140000
0!
#145000
b111100 (
b111100 B
b111100 F
b111000 '
b111000 @
b111000 C
b111000 D
b1111 #
1!
#150000
0!
#155000
b1000000 (
b1000000 B
b1000000 F
b111100 '
b111100 @
b111100 C
b111100 D
b10000 #
1!
#160000
0!
#165000
b1000100 (
b1000100 B
b1000100 F
b1000000 '
b1000000 @
b1000000 C
b1000000 D
b10001 #
1!
#170000
0!
#175000
b1001000 (
b1001000 B
b1001000 F
b1000100 '
b1000100 @
b1000100 C
b1000100 D
b10010 #
1!
#180000
0!
#185000
b1001100 (
b1001100 B
b1001100 F
b1001000 '
b1001000 @
b1001000 C
b1001000 D
b10011 #
1!
#190000
0!
#195000
b1010000 (
b1010000 B
b1010000 F
b1001100 '
b1001100 @
b1001100 C
b1001100 D
b10100 #
1!
#200000
0!
#205000
b1010100 (
b1010100 B
b1010100 F
b1010000 '
b1010000 @
b1010000 C
b1010000 D
b10101 #
1!
#210000
0!
#215000
b1011000 (
b1011000 B
b1011000 F
b1010100 '
b1010100 @
b1010100 C
b1010100 D
b10110 #
1!
#220000
0!
#225000
b1011100 (
b1011100 B
b1011100 F
b1011000 '
b1011000 @
b1011000 C
b1011000 D
b10111 #
1!
#230000
0!
#235000
b1100000 (
b1100000 B
b1100000 F
b1011100 '
b1011100 @
b1011100 C
b1011100 D
b11000 #
1!
#240000
0!
#245000
b1100100 (
b1100100 B
b1100100 F
b1100000 '
b1100000 @
b1100000 C
b1100000 D
b11001 #
1!
#250000
0!
#255000
b1101000 (
b1101000 B
b1101000 F
b1100100 '
b1100100 @
b1100100 C
b1100100 D
b11010 #
1!
#260000
0!
#265000
b1101100 (
b1101100 B
b1101100 F
b1101000 '
b1101000 @
b1101000 C
b1101000 D
b11011 #
1!
#270000
0!
#275000
b1110000 (
b1110000 B
b1110000 F
b1101100 '
b1101100 @
b1101100 C
b1101100 D
b11100 #
1!
#280000
0!
#285000
b1110100 (
b1110100 B
b1110100 F
b1110000 '
b1110000 @
b1110000 C
b1110000 D
b11101 #
1!
#290000
0!
#295000
b1111000 (
b1111000 B
b1111000 F
b1110100 '
b1110100 @
b1110100 C
b1110100 D
b11110 #
1!
#300000
0!
#305000
b1111100 (
b1111100 B
b1111100 F
b1111000 '
b1111000 @
b1111000 C
b1111000 D
b11111 #
1!
#310000
0!
#315000
b10000000 (
b10000000 B
b10000000 F
b1111100 '
b1111100 @
b1111100 C
b1111100 D
b100000 #
1!
#320000
0!
#325000
x&
x+
bx 0
bx L
bx P
bx 9
bx 7
bx 4
bx G
bx -
bx K
bx O
bx J
bx .
bx I
bx N
bx H
b10000100 (
b10000100 B
b10000100 F
bx *
bx 8
bx ?
b10000000 '
b10000000 @
b10000000 C
b10000000 D
b100001 #
1!
#330000
0!
#335000
b10001000 (
b10001000 B
b10001000 F
b10000100 '
b10000100 @
b10000100 C
b10000100 D
b100010 #
1!
#340000
0!
#345000
b10001100 (
b10001100 B
b10001100 F
b10001000 '
b10001000 @
b10001000 C
b10001000 D
b100011 #
1!
#350000
0!
#355000
b10010000 (
b10010000 B
b10010000 F
b10001100 '
b10001100 @
b10001100 C
b10001100 D
b100100 #
1!
#360000
0!
#365000
b10010100 (
b10010100 B
b10010100 F
b10010000 '
b10010000 @
b10010000 C
b10010000 D
b100101 #
1!
#370000
0!
#375000
b10011000 (
b10011000 B
b10011000 F
b10010100 '
b10010100 @
b10010100 C
b10010100 D
b100110 #
1!
#380000
0!
#385000
b10011100 (
b10011100 B
b10011100 F
b10011000 '
b10011000 @
b10011000 C
b10011000 D
b100111 #
1!
#390000
0!
#395000
b10100000 (
b10100000 B
b10100000 F
b10011100 '
b10011100 @
b10011100 C
b10011100 D
b101000 #
1!
#400000
0!
#405000
b10100100 (
b10100100 B
b10100100 F
b10100000 '
b10100000 @
b10100000 C
b10100000 D
b101001 #
1!
#410000
0!
#415000
b10101000 (
b10101000 B
b10101000 F
b10100100 '
b10100100 @
b10100100 C
b10100100 D
b101010 #
1!
#420000
0!
#425000
b10101100 (
b10101100 B
b10101100 F
b10101000 '
b10101000 @
b10101000 C
b10101000 D
b101011 #
1!
#430000
0!
#435000
b10110000 (
b10110000 B
b10110000 F
b10101100 '
b10101100 @
b10101100 C
b10101100 D
b101100 #
1!
#440000
0!
#445000
b10110100 (
b10110100 B
b10110100 F
b10110000 '
b10110000 @
b10110000 C
b10110000 D
b101101 #
1!
#450000
0!
#455000
b10111000 (
b10111000 B
b10111000 F
b10110100 '
b10110100 @
b10110100 C
b10110100 D
b101110 #
1!
#460000
0!
#465000
b10111100 (
b10111100 B
b10111100 F
b10111000 '
b10111000 @
b10111000 C
b10111000 D
b101111 #
1!
#470000
0!
#475000
b11000000 (
b11000000 B
b11000000 F
b10111100 '
b10111100 @
b10111100 C
b10111100 D
b110000 #
1!
#480000
0!
#485000
b11000100 (
b11000100 B
b11000100 F
b11000000 '
b11000000 @
b11000000 C
b11000000 D
b110001 #
1!
#490000
0!
#495000
b11001000 (
b11001000 B
b11001000 F
b11000100 '
b11000100 @
b11000100 C
b11000100 D
b110010 #
1!
#500000
0!
#505000
b11001100 (
b11001100 B
b11001100 F
b11001000 '
b11001000 @
b11001000 C
b11001000 D
b110011 #
1!
#510000
0!
#515000
b11010000 (
b11010000 B
b11010000 F
b11001100 '
b11001100 @
b11001100 C
b11001100 D
b110100 #
1!
#520000
0!
#525000
b11010100 (
b11010100 B
b11010100 F
b11010000 '
b11010000 @
b11010000 C
b11010000 D
b110101 #
1!
#530000
0!
#535000
b11011000 (
b11011000 B
b11011000 F
b11010100 '
b11010100 @
b11010100 C
b11010100 D
b110110 #
1!
#540000
0!
#545000
b11011100 (
b11011100 B
b11011100 F
b11011000 '
b11011000 @
b11011000 C
b11011000 D
b110111 #
1!
#550000
0!
#555000
b11100000 (
b11100000 B
b11100000 F
b11011100 '
b11011100 @
b11011100 C
b11011100 D
b111000 #
1!
#560000
0!
#565000
b11100100 (
b11100100 B
b11100100 F
b11100000 '
b11100000 @
b11100000 C
b11100000 D
b111001 #
1!
#570000
0!
#575000
b11101000 (
b11101000 B
b11101000 F
b11100100 '
b11100100 @
b11100100 C
b11100100 D
b111010 #
1!
#580000
0!
#585000
b11101100 (
b11101100 B
b11101100 F
b11101000 '
b11101000 @
b11101000 C
b11101000 D
b111011 #
1!
#590000
0!
#595000
b11110000 (
b11110000 B
b11110000 F
b11101100 '
b11101100 @
b11101100 C
b11101100 D
b111100 #
1!
#600000
0!
#605000
b11110100 (
b11110100 B
b11110100 F
b11110000 '
b11110000 @
b11110000 C
b11110000 D
b111101 #
1!
#610000
0!
#615000
b11111000 (
b11111000 B
b11111000 F
b11110100 '
b11110100 @
b11110100 C
b11110100 D
b111110 #
1!
#620000
0!
#625000
b11111100 (
b11111100 B
b11111100 F
b11111000 '
b11111000 @
b11111000 C
b11111000 D
b111111 #
1!
#630000
0!
#635000
b100000000 (
b100000000 B
b100000000 F
b11111100 '
b11111100 @
b11111100 C
b11111100 D
b1000000 #
1!
#640000
0!
#645000
b100000100 (
b100000100 B
b100000100 F
b100000000 '
b100000000 @
b100000000 C
b100000000 D
b1000001 #
1!
#650000
0!
#655000
b100001000 (
b100001000 B
b100001000 F
b100000100 '
b100000100 @
b100000100 C
b100000100 D
b1000010 #
1!
#660000
0!
#665000
b100001100 (
b100001100 B
b100001100 F
b100001000 '
b100001000 @
b100001000 C
b100001000 D
b1000011 #
1!
#670000
0!
#675000
b100010000 (
b100010000 B
b100010000 F
b100001100 '
b100001100 @
b100001100 C
b100001100 D
b1000100 #
1!
#680000
0!
#685000
b100010100 (
b100010100 B
b100010100 F
b100010000 '
b100010000 @
b100010000 C
b100010000 D
b1000101 #
1!
#690000
0!
#695000
b100011000 (
b100011000 B
b100011000 F
b100010100 '
b100010100 @
b100010100 C
b100010100 D
b1000110 #
1!
#700000
0!
#705000
b100011100 (
b100011100 B
b100011100 F
b100011000 '
b100011000 @
b100011000 C
b100011000 D
b1000111 #
1!
#710000
0!
#715000
b100100000 (
b100100000 B
b100100000 F
b100011100 '
b100011100 @
b100011100 C
b100011100 D
b1001000 #
1!
#720000
0!
#725000
b100100100 (
b100100100 B
b100100100 F
b100100000 '
b100100000 @
b100100000 C
b100100000 D
b1001001 #
1!
#730000
0!
#735000
b100101000 (
b100101000 B
b100101000 F
b100100100 '
b100100100 @
b100100100 C
b100100100 D
b1001010 #
1!
#740000
0!
#745000
b100101100 (
b100101100 B
b100101100 F
b100101000 '
b100101000 @
b100101000 C
b100101000 D
b1001011 #
1!
#750000
0!
#755000
b100110000 (
b100110000 B
b100110000 F
b100101100 '
b100101100 @
b100101100 C
b100101100 D
b1001100 #
1!
#760000
0!
#765000
b100110100 (
b100110100 B
b100110100 F
b100110000 '
b100110000 @
b100110000 C
b100110000 D
b1001101 #
1!
#770000
0!
#775000
b100111000 (
b100111000 B
b100111000 F
b100110100 '
b100110100 @
b100110100 C
b100110100 D
b1001110 #
1!
#780000
0!
#785000
b100111100 (
b100111100 B
b100111100 F
b100111000 '
b100111000 @
b100111000 C
b100111000 D
b1001111 #
1!
#790000
0!
#795000
b101000000 (
b101000000 B
b101000000 F
b100111100 '
b100111100 @
b100111100 C
b100111100 D
b1010000 #
1!
#800000
0!
#805000
b101000100 (
b101000100 B
b101000100 F
b101000000 '
b101000000 @
b101000000 C
b101000000 D
b1010001 #
1!
#810000
0!
#815000
b101001000 (
b101001000 B
b101001000 F
b101000100 '
b101000100 @
b101000100 C
b101000100 D
b1010010 #
1!
#820000
0!
#825000
b101001100 (
b101001100 B
b101001100 F
b101001000 '
b101001000 @
b101001000 C
b101001000 D
b1010011 #
1!
#830000
0!
#835000
b101010000 (
b101010000 B
b101010000 F
b101001100 '
b101001100 @
b101001100 C
b101001100 D
b1010100 #
1!
#840000
0!
#845000
b101010100 (
b101010100 B
b101010100 F
b101010000 '
b101010000 @
b101010000 C
b101010000 D
b1010101 #
1!
#850000
0!
#855000
b101011000 (
b101011000 B
b101011000 F
b101010100 '
b101010100 @
b101010100 C
b101010100 D
b1010110 #
1!
#860000
0!
#865000
b101011100 (
b101011100 B
b101011100 F
b101011000 '
b101011000 @
b101011000 C
b101011000 D
b1010111 #
1!
#870000
0!
#875000
b101100000 (
b101100000 B
b101100000 F
b101011100 '
b101011100 @
b101011100 C
b101011100 D
b1011000 #
1!
#880000
0!
#885000
b101100100 (
b101100100 B
b101100100 F
b101100000 '
b101100000 @
b101100000 C
b101100000 D
b1011001 #
1!
#890000
0!
#895000
b101101000 (
b101101000 B
b101101000 F
b101100100 '
b101100100 @
b101100100 C
b101100100 D
b1011010 #
1!
#900000
0!
#905000
b101101100 (
b101101100 B
b101101100 F
b101101000 '
b101101000 @
b101101000 C
b101101000 D
b1011011 #
1!
#910000
0!
#915000
b101110000 (
b101110000 B
b101110000 F
b101101100 '
b101101100 @
b101101100 C
b101101100 D
b1011100 #
1!
#920000
0!
#925000
b101110100 (
b101110100 B
b101110100 F
b101110000 '
b101110000 @
b101110000 C
b101110000 D
b1011101 #
1!
#930000
0!
#935000
b101111000 (
b101111000 B
b101111000 F
b101110100 '
b101110100 @
b101110100 C
b101110100 D
b1011110 #
1!
#940000
0!
#945000
b101111100 (
b101111100 B
b101111100 F
b101111000 '
b101111000 @
b101111000 C
b101111000 D
b1011111 #
1!
#950000
0!
#955000
b110000000 (
b110000000 B
b110000000 F
b101111100 '
b101111100 @
b101111100 C
b101111100 D
b1100000 #
1!
#960000
0!
#965000
b110000100 (
b110000100 B
b110000100 F
b110000000 '
b110000000 @
b110000000 C
b110000000 D
b1100001 #
1!
#970000
0!
#975000
b110001000 (
b110001000 B
b110001000 F
b110000100 '
b110000100 @
b110000100 C
b110000100 D
b1100010 #
1!
#980000
0!
#985000
b110001100 (
b110001100 B
b110001100 F
b110001000 '
b110001000 @
b110001000 C
b110001000 D
b1100011 #
1!
#990000
0!
#995000
b110010000 (
b110010000 B
b110010000 F
b110001100 '
b110001100 @
b110001100 C
b110001100 D
b1100100 #
1!
#1000000
0!
#1005000
b110010100 (
b110010100 B
b110010100 F
b110010000 '
b110010000 @
b110010000 C
b110010000 D
b1100101 #
1!
