Lab3/Lab3test/alu.v
/***************************************************
Student Name:
Student ID:
***************************************************/
`timescale 1ns/1ps

module alu(
	input                   rst_n,         // negative reset            (input)
	input	signed    [32-1:0]	src1,          // 32 bits source 1          (input)
	input	signed     [32-1:0]	src2,          // 32 bits source 2          (input)
	input 	     [ 4-1:0] 	ALU_control,   // 4 bits ALU control input  (input)
	output reg   [32-1:0]	result,        // 32 bits result            (output)
	output reg              zero,          // 1 bit when the output is 0, zero must be set (output)
	output reg              cout,          // 1 bit carry out           (output)
	output reg              overflow       // 1 bit overflow            (output)
	);

/* Write your code HERE */
always @(negedge rst_n) begin
	if(~rst_n)begin
		result<=0;
		zero<=0;
		cout<=0;
		overflow<=0;

	end
end

always @(*)begin
	case(ALU_control)
			4'b0010:begin	//add
				{cout,result}={1'b0,src1}+{1'b0,src2};
			end
			4'b0110:begin	//sub
				{cout,result}={1'b0,src1}+{1'b0,~src2}+1;
			end
			4'b0000:begin	//and
				result=src1&src2;
			end
			4'b0001:begin	//or
				result=src1|src2;
			end
			4'b0011:begin	//xor
				result=src1^src2;
			end
			4'b0111:begin	//slt
				result=src1<src2;
				cout=0;
				end
			4'b1000:begin	//sll
				result=src1<<src2;
				cout=0;
			end
			4'b1001:begin	//sra
				result=src1>>>src2;
				cout=0;
			end
	endcase

end

always @(*) begin
	zero<=~(|result);
end

always @(*) begin
	if(ALU_control==4'b0010)begin
		//add
		if(src1[31]==0 && src2[31]==0 && result[31]==1)
			overflow=1;
		else if(src1[31]==1 && src2[31]==1 && result[31]==0)
			overflow=1;
		
		else
			overflow=0;
	end
	else if(ALU_control==4'b0110)begin
		//sub
		if(src1[31]==0 && src2[31]==1 && result[31]==1)
			overflow=1;
		else if(src1[31]==1 && src2[31]==0 && result[31]==0)
			overflow=1;
		else
			overflow=0;
	end
	else begin
		overflow=0;
	end
end



endmodule

Lab3/Lab3test/ALU_Ctrl.v
/***************************************************
Student Name: 
Student ID: 
***************************************************/

`timescale 1ns/1ps

module ALU_Ctrl(
	input	[4-1:0]	instr,
	input	[2-1:0]	ALUOp,
	output	reg [4-1:0] ALU_Ctrl_o
	);
	
/* Write your code HERE */
always @(*)begin
	if(ALUOp[1]==1)begin	//R-type
		case(instr)
			4'b0000:begin	//add
				ALU_Ctrl_o=4'b0010;
			end
			4'b0001:begin	//sub
				ALU_Ctrl_o=4'b0110;
			end
			4'b1110:begin	//and
				ALU_Ctrl_o=4'b0000;
			end
			4'b1100:begin	//or
				ALU_Ctrl_o=4'b0001;
			end
			4'b1000:begin	//xor
				ALU_Ctrl_o=4'b0011;
			end
			4'b0100:begin	//slt
				ALU_Ctrl_o=4'b0111;
			end
			4'b0010:begin	//sll
				ALU_Ctrl_o=4'b1000;
			end
			4'b1011:begin	//sra
				ALU_Ctrl_o=4'b1001;
			end


	endcase
	end
end



endmodule

Lab3/Lab3test/Adder.v
/***************************************************
Student Name: 
Student ID: 
***************************************************/

`timescale 1ns/1ps

module Adder(
    input  [32-1:0] src1_i,
	input  [32-1:0] src2_i,
	output [32-1:0] sum_o
	);
    
/* Write your code HERE */

assign sum_o=src1_i+src2_i;


endmodule

Lab3/Lab3test/Decoder.v
/***************************************************
Student Name: 
Student ID: 
***************************************************/

`timescale 1ns/1ps

module Decoder(
	input [32-1:0] 	instr_i,
	output wire			ALUSrc,
	output wire			RegWrite,
	output wire			Branch,
	output wire [2-1:0]	ALUOp
	);
	
//Internal Signals
wire	[7-1:0]		opcode;
wire 	[3-1:0]		funct3;
wire	[3-1:0]		Instr_field;
wire	[9-1:0]		Ctrl_o;

assign opcode=instr_i[6:0];
assign funct3=instr_i[14:12];

assign ALUsrc=0;
assign Branch=0;
assign RegWrite=0;
assign ALUOp=2'b10;



endmodule

Lab3/Lab3test/Reg_File.v
/***************************************************
Student Name: 
Student ID: 
***************************************************/

`timescale 1ns/1ps

module Reg_File(
    input           	 clk_i,
	input           	 rst_i,
    input  		[5-1:0]  RSaddr_i,
    input  		[5-1:0]  RTaddr_i,
    input  		[5-1:0]  RDaddr_i,
    input  		[32-1:0] RDdata_i,
    input           	 RegWrite_i,
    output wire [32-1:0] RSdata_o,
    output wire [32-1:0] RTdata_o
    );
          
reg signed [32-1:0] Reg_File [0:32-1];     

assign RSdata_o = Reg_File[RSaddr_i] ;
assign RTdata_o = Reg_File[RTaddr_i] ;   

always @(posedge clk_i) begin
    if(~rst_i) begin
	    Reg_File[0]  <= 0; Reg_File[1]  <= 1; Reg_File[2]  <= 2; Reg_File[3]  <= 0;
	    Reg_File[4]  <= 0; Reg_File[5]  <= 0; Reg_File[6]  <= 0; Reg_File[7]  <= 0;
        Reg_File[8]  <= 0; Reg_File[9]  <= 0; Reg_File[10] <= 0; Reg_File[11] <= 0;
	    Reg_File[12] <= 0; Reg_File[13] <= 0; Reg_File[14] <= 0; Reg_File[15] <= 0;
        Reg_File[16] <= 0; Reg_File[17] <= 0; Reg_File[18] <= 0; Reg_File[19] <= 0;      
        Reg_File[20] <= 0; Reg_File[21] <= 0; Reg_File[22] <= 0; Reg_File[23] <= 0;
        Reg_File[24] <= 0; Reg_File[25] <= 0; Reg_File[26] <= 0; Reg_File[27] <= 0;
        Reg_File[28] <= 0; Reg_File[29] <= 0; Reg_File[30] <= 0; Reg_File[31] <= 0;
	end
    else begin
        if(RegWrite_i) 
            Reg_File[RDaddr_i] <= RDdata_i;	
		else 
		    Reg_File[RDaddr_i] <= Reg_File[RDaddr_i];
	end
end

endmodule

Lab3/Lab3Code/Instr_Memory.v
/***************************************************
Student Name: 
Student ID: 
***************************************************/

`timescale 1ns/1ps

module Instr_Memory(
    input 	    [32-1:0] 	 addr_i,
	output wire [32-1:0] 	 instr_o
);

integer          i;
reg		[32-1:0] instruction_file	[0:31];

initial begin
    for ( i=0; i<32; i=i+1 )
	    instruction_file[i] = 32'b0;
    $readmemb("CO_test_data10.txt", instruction_file); 
end

assign	instr_o = instruction_file[addr_i/4];

endmodule

Lab4/ProgramCounter.v
/***************************************************
Student Name:許舒茵
Student ID: 0816080
***************************************************/

   `timescale 1ns/1ps

   module ProgramCounter(
       input               clk_i,
       input               rst_i,
       input      [32-1:0] pc_i,
       output reg [32-1:0] pc_o
   );

   always @(posedge clk_i) begin
       if(~rst_i)
           pc_o <= 0;
       else
           pc_o <= pc_i;
   end

   endmodule

Lab3/Lab3test/Simple_Single_CPU.v
/***************************************************
Student Name: 
Student ID: 
***************************************************/

`timescale 1ns/1ps
module Simple_Single_CPU(
	input clk_i,
	input rst_i
	);

//Internal Signles
wire [31:0] pc_i;
wire [31:0] pc_o;
wire [31:0] instr;
wire [31:0] ALUresult;
wire RegWrite;
wire [31:0] RSdata_o;
wire [31:0] RTdata_o;
wire ALUSrc;
wire [1:0] ALUOp;
wire [3:0]ALU_control;
wire zero,cout,overflow;
wire [31:0]imm_4 = 4;
		
ProgramCounter PC(
        .clk_i(clk_i),      
	    .rst_i (rst_i),     
	    .pc_i(pc_i) ,   
	    .pc_o(pc_o) 
	    );

Instr_Memory IM(
        .addr_i(pc_o),  
	    .instr_o(instr)    
	    );
		
Reg_File RF(
        .clk_i(clk_i),      
	    .rst_i(rst_i) ,     
        .RSaddr_i(instr[19:15]) ,  
        .RTaddr_i(instr[24:20]) ,  
        .RDaddr_i(instr[11:7]) ,  
        .RDdata_i(ALUresult)  , 
        .RegWrite_i (RegWrite),
        .RSdata_o(RSdata_o) ,  
        .RTdata_o(RTdata_o)   
        );
		
Decoder Decoder(
	.instr_i(instr),
	.ALUSrc(ALUSrc),
	.RegWrite(RegWrite),
	.ALUOp(ALUOp)
	    );	

Adder PC_plus_4_Adder(
	.src1_i(pc_i),
	.src2_i(imm_4),
	.sum_o(pc_o)
	    );
		
	
			
ALU_Ctrl ALU_Ctrl(
	.instr({instr[30],instr[14:12]}),
	.ALUOp(ALUOp),
	.ALU_Ctrl_o(ALU_control)
		);
		
alu alu(
	.rst_n(rst_i), 
	.src1(RSdata_o),
	.src2(RTdata_o),
	.ALU_control(ALU_control),
	.result(ALUresult),
	.zero(zero), 
	.cout(cout),
	.overflow(overflow)    
		);
	
		
endmodule

Lab3/Lab3test/testbench.v
/***************************************************
Student Name: 
Student ID: 
***************************************************/

`timescale 1ns/1ps
`define CYCLE_TIME 10			
`define END_COUNT 100

module testbench;

reg         clk;
reg         rst_n;
integer     count;
integer     fp_w;

Simple_Single_CPU cpu(
        .clk_i(clk),
		.rst_i(rst_n)
		);

always #(`CYCLE_TIME/2) clk = ~clk;	

initial begin
	$dumpfile("lab3.vcd");
    $dumpvars(0, testbench);
end
	
initial  begin
    fp_w = $fopen("CO_Result.txt");
	clk = 0;
    rst_n = 0;
	count = 0;
    #(`CYCLE_TIME)      rst_n = 1;
    #(`CYCLE_TIME*`END_COUNT)	$fclose(fp_w); $finish;
end

always@(posedge clk) begin
    count = count + 1;
	if( count == `END_COUNT ) begin 
    $fdisplay(fp_w, "r0 = %3d, r1 = %3d, r2 = %3d, r3 = %3d, \nr4 = %3d, r5 = %3d, r6 = %3d, r7 = %3d, \nr8 = %3d, r9 = %3d, r10 = %2d, r11 = %2d",
	          cpu.RF.Reg_File[0], cpu.RF.Reg_File[1], cpu.RF.Reg_File[2], cpu.RF.Reg_File[3], cpu.RF.Reg_File[4], 
			  cpu.RF.Reg_File[5], cpu.RF.Reg_File[6], cpu.RF.Reg_File[7], cpu.RF.Reg_File[8], cpu.RF.Reg_File[9], 
			  cpu.RF.Reg_File[10],cpu.RF.Reg_File[11]
			  );
	$display("r0 = %3d, r1 = %3d, r2 = %3d, r3 = %3d, \nr4 = %3d, r5 = %3d, r6 = %3d, r7 = %3d, \nr8 = %3d, r9 = %3d, r10 = %2d, r11 = %2d",
	          cpu.RF.Reg_File[0], cpu.RF.Reg_File[1], cpu.RF.Reg_File[2], cpu.RF.Reg_File[3], cpu.RF.Reg_File[4], 
			  cpu.RF.Reg_File[5], cpu.RF.Reg_File[6], cpu.RF.Reg_File[7], cpu.RF.Reg_File[8], cpu.RF.Reg_File[9], 
			  cpu.RF.Reg_File[10],cpu.RF.Reg_File[11]
			  );
	end
end
  
endmodule

Lab3/Lab3test/lab3.vcd
$date
	Wed Apr 21 21:51:04 2021
$end
$version
	Icarus Verilog
$end
$timescale
	1ps
$end
$scope module testbench $end
$var reg 1 ! clk $end
$var reg 1 " rst_n $end
$var integer 32 # count [31:0] $end
$var integer 32 $ fp_w [31:0] $end
$scope module cpu $end
$var wire 2 % ALUOp [1:0] $end
$var wire 1 & ALUSrc $end
$var wire 1 ' RegWrite $end
$var wire 1 ! clk_i $end
$var wire 32 ( imm_4 [31:0] $end
$var wire 32 ) pc_i [31:0] $end
$var wire 32 * pc_o [31:0] $end
$var wire 1 " rst_i $end
$var wire 1 + zero $end
$var wire 1 , overflow $end
$var wire 32 - instr [31:0] $end
$var wire 1 . cout $end
$var wire 32 / RTdata_o [31:0] $end
$var wire 32 0 RSdata_o [31:0] $end
$var wire 32 1 ALUresult [31:0] $end
$var wire 4 2 ALU_control [3:0] $end
$scope module ALU_Ctrl $end
$var wire 2 3 ALUOp [1:0] $end
$var wire 4 4 instr [3:0] $end
$var reg 4 5 ALU_Ctrl_o [3:0] $end
$upscope $end
$scope module Decoder $end
$var wire 2 6 ALUOp [1:0] $end
$var wire 1 & ALUSrc $end
$var wire 1 7 ALUsrc $end
$var wire 1 8 Branch $end
$var wire 1 ' RegWrite $end
$var wire 7 9 opcode [6:0] $end
$var wire 32 : instr_i [31:0] $end
$var wire 3 ; funct3 [2:0] $end
$upscope $end
$scope module IM $end
$var wire 32 < addr_i [31:0] $end
$var wire 32 = instr_o [31:0] $end
$var integer 32 > i [31:0] $end
$upscope $end
$scope module PC $end
$var wire 1 ! clk_i $end
$var wire 32 ? pc_i [31:0] $end
$var wire 1 " rst_i $end
$var reg 32 @ pc_o [31:0] $end
$upscope $end
$scope module PC_plus_4_Adder $end
$var wire 32 A src1_i [31:0] $end
$var wire 32 B src2_i [31:0] $end
$var wire 32 C sum_o [31:0] $end
$upscope $end
$scope module RF $end
$var wire 5 D RDaddr_i [4:0] $end
$var wire 5 E RSaddr_i [4:0] $end
$var wire 32 F RSdata_o [31:0] $end
$var wire 5 G RTaddr_i [4:0] $end
$var wire 32 H RTdata_o [31:0] $end
$var wire 1 ' RegWrite_i $end
$var wire 1 ! clk_i $end
$var wire 1 " rst_i $end
$var wire 32 I RDdata_i [31:0] $end
$upscope $end
$scope module alu $end
$var wire 4 J ALU_control [3:0] $end
$var wire 1 " rst_n $end
$var wire 32 K src1 [31:0] $end
$var wire 32 L src2 [31:0] $end
$var reg 1 . cout $end
$var reg 1 , overflow $end
$var reg 32 M result [31:0] $end
$var reg 1 + zero $end
$upscope $end
$upscope $end
$upscope $end
$enddefinitions $end
#0
$dumpvars
b0 M
bx L
bx K
bx J
b0 I
bx H
bx G
bx F
bx E
bx D
bx C
b100 B
bz A
bx @
bz ?
b100000 >
bx =
bx <
bx ;
bx :
bx 9
08
07
b10 6
bx 5
bx 4
b10 3
bx 2
b0 1
bx 0
bx /
0.
bx -
0,
1+
bx *
bz )
b100 (
0'
z&
b10 %
b10 $
b0 #
0"
0!
$end
#5000
b0 @
b1 #
1!
#10000
0!
1"
#15000
bz @
b10 #
1!
#20000
0!
#25000
b11 #
1!
#30000
0!
#35000
b100 #
1!
#40000
0!
#45000
b101 #
1!
#50000
0!
#55000
b110 #
1!
#60000
0!
#65000
b111 #
1!
#70000
0!
#75000
b1000 #
1!
#80000
0!
#85000
b1001 #
1!
#90000
0!
#95000
b1010 #
1!
#100000
0!
#105000
b1011 #
1!
#110000
0!
#115000
b1100 #
1!
#120000
0!
#125000
b1101 #
1!
#130000
0!
#135000
b1110 #
1!
#140000
0!
#145000
b1111 #
1!
#150000
0!
#155000
b10000 #
1!
#160000
0!
#165000
b10001 #
1!
#170000
0!
#175000
b10010 #
1!
#180000
0!
#185000
b10011 #
1!
#190000
0!
#195000
b10100 #
1!
#200000
0!
#205000
b10101 #
1!
#210000
0!
#215000
b10110 #
1!
#220000
0!
#225000
b10111 #
1!
#230000
0!
#235000
b11000 #
1!
#240000
0!
#245000
b11001 #
1!
#250000
0!
#255000
b11010 #
1!
#260000
0!
#265000
b11011 #
1!
#270000
0!
#275000
b11100 #
1!
#280000
0!
#285000
b11101 #
1!
#290000
0!
#295000
b11110 #
1!
#300000
0!
#305000
b11111 #
1!
#310000
0!
#315000
b100000 #
1!
#320000
0!
#325000
b100001 #
1!
#330000
0!
#335000
b100010 #
1!
#340000
0!
#345000
b100011 #
1!
#350000
0!
#355000
b100100 #
1!
#360000
0!
#365000
b100101 #
1!
#370000
0!
#375000
b100110 #
1!
#380000
0!
#385000
b100111 #
1!
#390000
0!
#395000
b101000 #
1!
#400000
0!
#405000
b101001 #
1!
#410000
0!
#415000
b101010 #
1!
#420000
0!
#425000
b101011 #
1!
#430000
0!
#435000
b101100 #
1!
#440000
0!
#445000
b101101 #
1!
#450000
0!
#455000
b101110 #
1!
#460000
0!
#465000
b101111 #
1!
#470000
0!
#475000
b110000 #
1!
#480000
0!
#485000
b110001 #
1!
#490000
0!
#495000
b110010 #
1!
#500000
0!
#505000
b110011 #
1!
#510000
0!
#515000
b110100 #
1!
#520000
0!
#525000
b110101 #
1!
#530000
0!
#535000
b110110 #
1!
#540000
0!
#545000
b110111 #
1!
#550000
0!
#555000
b111000 #
1!
#560000
0!
#565000
b111001 #
1!
#570000
0!
#575000
b111010 #
1!
#580000
0!
#585000
b111011 #
1!
#590000
0!
#595000
b111100 #
1!
#600000
0!
#605000
b111101 #
1!
#610000
0!
#615000
b111110 #
1!
#620000
0!
#625000
b111111 #
1!
#630000
0!
#635000
b1000000 #
1!
#640000
0!
#645000
b1000001 #
1!
#650000
0!
#655000
b1000010 #
1!
#660000
0!
#665000
b1000011 #
1!
#670000
0!
#675000
b1000100 #
1!
#680000
0!
#685000
b1000101 #
1!
#690000
0!
#695000
b1000110 #
1!
#700000
0!
#705000
b1000111 #
1!
#710000
0!
#715000
b1001000 #
1!
#720000
0!
#725000
b1001001 #
1!
#730000
0!
#735000
b1001010 #
1!
#740000
0!
#745000
b1001011 #
1!
#750000
0!
#755000
b1001100 #
1!
#760000
0!
#765000
b1001101 #
1!
#770000
0!
#775000
b1001110 #
1!
#780000
0!
#785000
b1001111 #
1!
#790000
0!
#795000
b1010000 #
1!
#800000
0!
#805000
b1010001 #
1!
#810000
0!
#815000
b1010010 #
1!
#820000
0!
#825000
b1010011 #
1!
#830000
0!
#835000
b1010100 #
1!
#840000
0!
#845000
b1010101 #
1!
#850000
0!
#855000
b1010110 #
1!
#860000
0!
#865000
b1010111 #
1!
#870000
0!
#875000
b1011000 #
1!
#880000
0!
#885000
b1011001 #
1!
#890000
0!
#895000
b1011010 #
1!
#900000
0!
#905000
b1011011 #
1!
#910000
0!
#915000
b1011100 #
1!
#920000
0!
#925000
b1011101 #
1!
#930000
0!
#935000
b1011110 #
1!
#940000
0!
#945000
b1011111 #
1!
#950000
0!
#955000
b1100000 #
1!
#960000
0!
#965000
b1100001 #
1!
#970000
0!
#975000
b1100010 #
1!
#980000
0!
#985000
b1100011 #
1!
#990000
0!
#995000
b1100100 #
1!
#1000000
0!
#1005000
b1100101 #
1!
